neural_response_map/__init__.py
neural_response_map/mappers.py
neural_response_map-1.0.0.dist-info/METADATA
neural_response_map-1.0.0.dist-info/WHEEL
neural_response_map-1.0.0.dist-info/top_level.txt
neural_response_map-1.0.0.dist-info/RECORD
