Metadata-Version: 2.1
Name: neural-response-map
Version: 1.0.0
Summary: Library to visualize the activations of the hidden layers of artificial neural networks
Home-page: https://github.com/joancerretani/NeuralResponseMap
Author: Joan Alberto Cerretani
Author-email: joancerretani@gmail.com
License: MIT
Keywords: deep-learning,visualization,data-analysis
Platform: UNKNOWN
Requires-Dist: numpy
Requires-Dist: scipy
Requires-Dist: sklearn
Requires-Dist: tensorflow
Requires-Dist: matplotlib
